{
    "cod": "200",
    "message": 0,
    "cnt": 40,
    "list": [
        {
            "dt": 1694282400,
            "main": {
                "temp": 23.29,
                "feels_like": 23.71,
                "temp_min": 20.85,
                "temp_max": 23.29,
                "pressure": 1015,
                "sea_level": 1015,
                "grnd_level": 1014,
                "humidity": 78,
                "temp_kf": 2.44
            },
            "weather": [
                {
                    "id": 500,
                    "main": "Rain",
                    "description": "light rain",
                    "icon": "10d"
                }
            ],
            "clouds": {
                "all": 61
            },
            "wind": {
                "speed": 0.85,
                "deg": 181,
                "gust": 1.43
            },
            "visibility": 10000,
            "pop": 0.81,
            "rain": {
                "3h": 2.43
            },
            "sys": {
                "pod": "d"
            },
            "dt_txt": "2023-09-09 18:00:00"
        },
        {
            "dt": 1694293200,
            "main": {
                "temp": 20.33,
                "feels_like": 20.72,
                "temp_min": 18.24,
                "temp_max": 20.33,
                "pressure": 1016,
                "sea_level": 1016,
                "grnd_level": 1016,
                "humidity": 88,
                "temp_kf": 2.09
            },
            "weather": [
                {
                    "id": 501,
                    "main": "Rain",
                    "description": "moderate rain",
                    "icon": "10n"
                }
            ],
            "clouds": {
                "all": 74
            },
            "wind": {
                "speed": 1.14,
                "deg": 259,
                "gust": 1.25
            },
            "visibility": 10000,
            "pop": 0.61,
            "rain": {
                "3h": 4.54
            },
            "sys": {
                "pod": "n"
            },
            "dt_txt": "2023-09-09 21:00:00"
        },
        {
            "dt": 1694304000,
            "main": {
                "temp": 17.52,
                "feels_like": 17.83,
                "temp_min": 17.52,
                "temp_max": 17.52,
                "pressure": 1016,
                "sea_level": 1016,
                "grnd_level": 1015,
                "humidity": 96,
                "temp_kf": 0
            },
            "weather": [
                {
                    "id": 500,
                    "main": "Rain",
                    "description": "light rain",
                    "icon": "10n"
                }
            ],
            "clouds": {
                "all": 41
            },
            "wind": {
                "speed": 1.43,
                "deg": 310,
                "gust": 1.49
            },
            "visibility": 10000,
            "pop": 0.61,
            "rain": {
                "3h": 0.59
            },
            "sys": {
                "pod": "n"
            },
            "dt_txt": "2023-09-10 00:00:00"
        },
        {
            "dt": 1694314800,
            "main": {
                "temp": 16.92,
                "feels_like": 17.17,
                "temp_min": 16.92,
                "temp_max": 16.92,
                "pressure": 1016,
                "sea_level": 1016,
                "grnd_level": 1014,
                "humidity": 96,
                "temp_kf": 0
            },
            "weather": [
                {
                    "id": 801,
                    "main": "Clouds",
                    "description": "few clouds",
                    "icon": "02n"
                }
            ],
            "clouds": {
                "all": 11
            },
            "wind": {
                "speed": 0.24,
                "deg": 286,
                "gust": 0.47
            },
            "visibility": 10000,
            "pop": 0,
            "sys": {
                "pod": "n"
            },
            "dt_txt": "2023-09-10 03:00:00"
        },
        {
            "dt": 1694325600,
            "main": {
                "temp": 16.49,
                "feels_like": 16.7,
                "temp_min": 16.49,
                "temp_max": 16.49,
                "pressure": 1016,
                "sea_level": 1016,
                "grnd_level": 1014,
                "humidity": 96,
                "temp_kf": 0
            },
            "weather": [
                {
                    "id": 802,
                    "main": "Clouds",
                    "description": "scattered clouds",
                    "icon": "03d"
                }
            ],
            "clouds": {
                "all": 42
            },
            "wind": {
                "speed": 0.42,
                "deg": 326,
                "gust": 0.57
            },
            "visibility": 10000,
            "pop": 0,
            "sys": {
                "pod": "d"
            },
            "dt_txt": "2023-09-10 06:00:00"
        },
        {
            "dt": 1694336400,
            "main": {
                "temp": 19.75,
                "feels_like": 20.08,
                "temp_min": 19.75,
                "temp_max": 19.75,
                "pressure": 1015,
                "sea_level": 1015,
                "grnd_level": 1014,
                "humidity": 88,
                "temp_kf": 0
            },
            "weather": [
                {
                    "id": 803,
                    "main": "Clouds",
                    "description": "broken clouds",
                    "icon": "04d"
                }
            ],
            "clouds": {
                "all": 65
            },
            "wind": {
                "speed": 1.1,
                "deg": 20,
                "gust": 1.02
            },
            "visibility": 10000,
            "pop": 0,
            "sys": {
                "pod": "d"
            },
            "dt_txt": "2023-09-10 09:00:00"
        },
        {
            "dt": 1694347200,
            "main": {
                "temp": 21.83,
                "feels_like": 22.08,
                "temp_min": 21.83,
                "temp_max": 21.83,
                "pressure": 1014,
                "sea_level": 1014,
                "grnd_level": 1013,
                "humidity": 77,
                "temp_kf": 0
            },
            "weather": [
                {
                    "id": 803,
                    "main": "Clouds",
                    "description": "broken clouds",
                    "icon": "04d"
                }
            ],
            "clouds": {
                "all": 74
            },
            "wind": {
                "speed": 1.64,
                "deg": 44,
                "gust": 0.93
            },
            "visibility": 8588,
            "pop": 0.09,
            "sys": {
                "pod": "d"
            },
            "dt_txt": "2023-09-10 12:00:00"
        },
        {
            "dt": 1694358000,
            "main": {
                "temp": 20.98,
                "feels_like": 21.25,
                "temp_min": 20.98,
                "temp_max": 20.98,
                "pressure": 1013,
                "sea_level": 1013,
                "grnd_level": 1011,
                "humidity": 81,
                "temp_kf": 0
            },
            "weather": [
                {
                    "id": 500,
                    "main": "Rain",
                    "description": "light rain",
                    "icon": "10d"
                }
            ],
            "clouds": {
                "all": 85
            },
            "wind": {
                "speed": 2.12,
                "deg": 82,
                "gust": 1.7
            },
            "visibility": 10000,
            "pop": 0.6,
            "rain": {
                "3h": 1.17
            },
            "sys": {
                "pod": "d"
            },
            "dt_txt": "2023-09-10 15:00:00"
        },
        {
            "dt": 1694368800,
            "main": {
                "temp": 18.52,
                "feels_like": 18.91,
                "temp_min": 18.52,
                "temp_max": 18.52,
                "pressure": 1012,
                "sea_level": 1012,
                "grnd_level": 1010,
                "humidity": 95,
                "temp_kf": 0
            },
            "weather": [
                {
                    "id": 501,
                    "main": "Rain",
                    "description": "moderate rain",
                    "icon": "10d"
                }
            ],
            "clouds": {
                "all": 92
            },
            "wind": {
                "speed": 1.02,
                "deg": 166,
                "gust": 1.17
            },
            "visibility": 10000,
            "pop": 0.97,
            "rain": {
                "3h": 4.6
            },
            "sys": {
                "pod": "d"
            },
            "dt_txt": "2023-09-10 18:00:00"
        },
        {
            "dt": 1694379600,
            "main": {
                "temp": 18.23,
                "feels_like": 18.59,
                "temp_min": 18.23,
                "temp_max": 18.23,
                "pressure": 1012,
                "sea_level": 1012,
                "grnd_level": 1011,
                "humidity": 95,
                "temp_kf": 0
            },
            "weather": [
                {
                    "id": 500,
                    "main": "Rain",
                    "description": "light rain",
                    "icon": "10n"
                }
            ],
            "clouds": {
                "all": 100
            },
            "wind": {
                "speed": 1.6,
                "deg": 220,
                "gust": 1.71
            },
            "visibility": 10000,
            "pop": 0.83,
            "rain": {
                "3h": 2.31
            },
            "sys": {
                "pod": "n"
            },
            "dt_txt": "2023-09-10 21:00:00"
        },
        {
            "dt": 1694390400,
            "main": {
                "temp": 17.8,
                "feels_like": 18.14,
                "temp_min": 17.8,
                "temp_max": 17.8,
                "pressure": 1012,
                "sea_level": 1012,
                "grnd_level": 1010,
                "humidity": 96,
                "temp_kf": 0
            },
            "weather": [
                {
                    "id": 500,
                    "main": "Rain",
                    "description": "light rain",
                    "icon": "10n"
                }
            ],
            "clouds": {
                "all": 100
            },
            "wind": {
                "speed": 2.69,
                "deg": 260,
                "gust": 5.19
            },
            "visibility": 10000,
            "pop": 0.73,
            "rain": {
                "3h": 0.24
            },
            "sys": {
                "pod": "n"
            },
            "dt_txt": "2023-09-11 00:00:00"
        },
        {
            "dt": 1694401200,
            "main": {
                "temp": 15.03,
                "feels_like": 15.12,
                "temp_min": 15.03,
                "temp_max": 15.03,
                "pressure": 1012,
                "sea_level": 1012,
                "grnd_level": 1010,
                "humidity": 97,
                "temp_kf": 0
            },
            "weather": [
                {
                    "id": 804,
                    "main": "Clouds",
                    "description": "overcast clouds",
                    "icon": "04n"
                }
            ],
            "clouds": {
                "all": 92
            },
            "wind": {
                "speed": 3.26,
                "deg": 263,
                "gust": 5.95
            },
            "visibility": 10000,
            "pop": 0,
            "sys": {
                "pod": "n"
            },
            "dt_txt": "2023-09-11 03:00:00"
        },
        {
            "dt": 1694412000,
            "main": {
                "temp": 14.31,
                "feels_like": 14.33,
                "temp_min": 14.31,
                "temp_max": 14.31,
                "pressure": 1012,
                "sea_level": 1012,
                "grnd_level": 1011,
                "humidity": 97,
                "temp_kf": 0
            },
            "weather": [
                {
                    "id": 804,
                    "main": "Clouds",
                    "description": "overcast clouds",
                    "icon": "04d"
                }
            ],
            "clouds": {
                "all": 85
            },
            "wind": {
                "speed": 3.05,
                "deg": 260,
                "gust": 6.24
            },
            "visibility": 10000,
            "pop": 0,
            "sys": {
                "pod": "d"
            },
            "dt_txt": "2023-09-11 06:00:00"
        },
        {
            "dt": 1694422800,
            "main": {
                "temp": 15.46,
                "feels_like": 15.44,
                "temp_min": 15.46,
                "temp_max": 15.46,
                "pressure": 1013,
                "sea_level": 1013,
                "grnd_level": 1012,
                "humidity": 91,
                "temp_kf": 0
            },
            "weather": [
                {
                    "id": 804,
                    "main": "Clouds",
                    "description": "overcast clouds",
                    "icon": "04d"
                }
            ],
            "clouds": {
                "all": 100
            },
            "wind": {
                "speed": 2.98,
                "deg": 273,
                "gust": 4.7
            },
            "visibility": 10000,
            "pop": 0.07,
            "sys": {
                "pod": "d"
            },
            "dt_txt": "2023-09-11 09:00:00"
        },
        {
            "dt": 1694433600,
            "main": {
                "temp": 14.76,
                "feels_like": 14.75,
                "temp_min": 14.76,
                "temp_max": 14.76,
                "pressure": 1014,
                "sea_level": 1014,
                "grnd_level": 1012,
                "humidity": 94,
                "temp_kf": 0
            },
            "weather": [
                {
                    "id": 500,
                    "main": "Rain",
                    "description": "light rain",
                    "icon": "10d"
                }
            ],
            "clouds": {
                "all": 100
            },
            "wind": {
                "speed": 2.12,
                "deg": 283,
                "gust": 3.19
            },
            "visibility": 10000,
            "pop": 0.44,
            "rain": {
                "3h": 0.6
            },
            "sys": {
                "pod": "d"
            },
            "dt_txt": "2023-09-11 12:00:00"
        },
        {
            "dt": 1694444400,
            "main": {
                "temp": 14.57,
                "feels_like": 14.54,
                "temp_min": 14.57,
                "temp_max": 14.57,
                "pressure": 1014,
                "sea_level": 1014,
                "grnd_level": 1012,
                "humidity": 94,
                "temp_kf": 0
            },
            "weather": [
                {
                    "id": 500,
                    "main": "Rain",
                    "description": "light rain",
                    "icon": "10d"
                }
            ],
            "clouds": {
                "all": 100
            },
            "wind": {
                "speed": 1.82,
                "deg": 276,
                "gust": 2.81
            },
            "visibility": 10000,
            "pop": 0.76,
            "rain": {
                "3h": 1.43
            },
            "sys": {
                "pod": "d"
            },
            "dt_txt": "2023-09-11 15:00:00"
        },
        {
            "dt": 1694455200,
            "main": {
                "temp": 14.14,
                "feels_like": 14.12,
                "temp_min": 14.14,
                "temp_max": 14.14,
                "pressure": 1014,
                "sea_level": 1014,
                "grnd_level": 1013,
                "humidity": 96,
                "temp_kf": 0
            },
            "weather": [
                {
                    "id": 500,
                    "main": "Rain",
                    "description": "light rain",
                    "icon": "10d"
                }
            ],
            "clouds": {
                "all": 100
            },
            "wind": {
                "speed": 1.18,
                "deg": 289,
                "gust": 2.17
            },
            "visibility": 10000,
            "pop": 0.83,
            "rain": {
                "3h": 1.19
            },
            "sys": {
                "pod": "d"
            },
            "dt_txt": "2023-09-11 18:00:00"
        },
        {
            "dt": 1694466000,
            "main": {
                "temp": 13.79,
                "feels_like": 13.76,
                "temp_min": 13.79,
                "temp_max": 13.79,
                "pressure": 1014,
                "sea_level": 1014,
                "grnd_level": 1013,
                "humidity": 97,
                "temp_kf": 0
            },
            "weather": [
                {
                    "id": 500,
                    "main": "Rain",
                    "description": "light rain",
                    "icon": "10n"
                }
            ],
            "clouds": {
                "all": 100
            },
            "wind": {
                "speed": 1.55,
                "deg": 291,
                "gust": 2.46
            },
            "visibility": 10000,
            "pop": 0.64,
            "rain": {
                "3h": 2.22
            },
            "sys": {
                "pod": "n"
            },
            "dt_txt": "2023-09-11 21:00:00"
        },
        {
            "dt": 1694476800,
            "main": {
                "temp": 13.61,
                "feels_like": 13.56,
                "temp_min": 13.61,
                "temp_max": 13.61,
                "pressure": 1014,
                "sea_level": 1014,
                "grnd_level": 1013,
                "humidity": 97,
                "temp_kf": 0
            },
            "weather": [
                {
                    "id": 500,
                    "main": "Rain",
                    "description": "light rain",
                    "icon": "10n"
                }
            ],
            "clouds": {
                "all": 100
            },
            "wind": {
                "speed": 1.76,
                "deg": 320,
                "gust": 2.98
            },
            "visibility": 10000,
            "pop": 0.8,
            "rain": {
                "3h": 1.6
            },
            "sys": {
                "pod": "n"
            },
            "dt_txt": "2023-09-12 00:00:00"
        },
        {
            "dt": 1694487600,
            "main": {
                "temp": 13.08,
                "feels_like": 12.98,
                "temp_min": 13.08,
                "temp_max": 13.08,
                "pressure": 1015,
                "sea_level": 1015,
                "grnd_level": 1013,
                "humidity": 97,
                "temp_kf": 0
            },
            "weather": [
                {
                    "id": 500,
                    "main": "Rain",
                    "description": "light rain",
                    "icon": "10n"
                }
            ],
            "clouds": {
                "all": 100
            },
            "wind": {
                "speed": 2.56,
                "deg": 346,
                "gust": 4.57
            },
            "visibility": 10000,
            "pop": 0.43,
            "rain": {
                "3h": 0.14
            },
            "sys": {
                "pod": "n"
            },
            "dt_txt": "2023-09-12 03:00:00"
        },
        {
            "dt": 1694498400,
            "main": {
                "temp": 12.48,
                "feels_like": 12.26,
                "temp_min": 12.48,
                "temp_max": 12.48,
                "pressure": 1016,
                "sea_level": 1016,
                "grnd_level": 1015,
                "humidity": 95,
                "temp_kf": 0
            },
            "weather": [
                {
                    "id": 500,
                    "main": "Rain",
                    "description": "light rain",
                    "icon": "10d"
                }
            ],
            "clouds": {
                "all": 100
            },
            "wind": {
                "speed": 3.33,
                "deg": 3,
                "gust": 5.67
            },
            "visibility": 10000,
            "pop": 0.47,
            "rain": {
                "3h": 0.28
            },
            "sys": {
                "pod": "d"
            },
            "dt_txt": "2023-09-12 06:00:00"
        },
        {
            "dt": 1694509200,
            "main": {
                "temp": 12.56,
                "feels_like": 12.2,
                "temp_min": 12.56,
                "temp_max": 12.56,
                "pressure": 1018,
                "sea_level": 1018,
                "grnd_level": 1017,
                "humidity": 89,
                "temp_kf": 0
            },
            "weather": [
                {
                    "id": 500,
                    "main": "Rain",
                    "description": "light rain",
                    "icon": "10d"
                }
            ],
            "clouds": {
                "all": 99
            },
            "wind": {
                "speed": 2.68,
                "deg": 352,
                "gust": 3.61
            },
            "visibility": 10000,
            "pop": 0.29,
            "rain": {
                "3h": 0.13
            },
            "sys": {
                "pod": "d"
            },
            "dt_txt": "2023-09-12 09:00:00"
        },
        {
            "dt": 1694520000,
            "main": {
                "temp": 15.05,
                "feels_like": 14.36,
                "temp_min": 15.05,
                "temp_max": 15.05,
                "pressure": 1018,
                "sea_level": 1018,
                "grnd_level": 1017,
                "humidity": 67,
                "temp_kf": 0
            },
            "weather": [
                {
                    "id": 803,
                    "main": "Clouds",
                    "description": "broken clouds",
                    "icon": "04d"
                }
            ],
            "clouds": {
                "all": 77
            },
            "wind": {
                "speed": 3.56,
                "deg": 10,
                "gust": 4.13
            },
            "visibility": 10000,
            "pop": 0,
            "sys": {
                "pod": "d"
            },
            "dt_txt": "2023-09-12 12:00:00"
        },
        {
            "dt": 1694530800,
            "main": {
                "temp": 15.78,
                "feels_like": 15.01,
                "temp_min": 15.78,
                "temp_max": 15.78,
                "pressure": 1019,
                "sea_level": 1019,
                "grnd_level": 1018,
                "humidity": 61,
                "temp_kf": 0
            },
            "weather": [
                {
                    "id": 801,
                    "main": "Clouds",
                    "description": "few clouds",
                    "icon": "02d"
                }
            ],
            "clouds": {
                "all": 12
            },
            "wind": {
                "speed": 3.15,
                "deg": 24,
                "gust": 4.27
            },
            "visibility": 10000,
            "pop": 0,
            "sys": {
                "pod": "d"
            },
            "dt_txt": "2023-09-12 15:00:00"
        },
        {
            "dt": 1694541600,
            "main": {
                "temp": 13.66,
                "feels_like": 13.01,
                "temp_min": 13.66,
                "temp_max": 13.66,
                "pressure": 1020,
                "sea_level": 1020,
                "grnd_level": 1018,
                "humidity": 74,
                "temp_kf": 0
            },
            "weather": [
                {
                    "id": 801,
                    "main": "Clouds",
                    "description": "few clouds",
                    "icon": "02d"
                }
            ],
            "clouds": {
                "all": 18
            },
            "wind": {
                "speed": 2.32,
                "deg": 3,
                "gust": 4.76
            },
            "visibility": 10000,
            "pop": 0,
            "sys": {
                "pod": "d"
            },
            "dt_txt": "2023-09-12 18:00:00"
        },
        {
            "dt": 1694552400,
            "main": {
                "temp": 10.47,
                "feels_like": 9.79,
                "temp_min": 10.47,
                "temp_max": 10.47,
                "pressure": 1021,
                "sea_level": 1021,
                "grnd_level": 1020,
                "humidity": 85,
                "temp_kf": 0
            },
            "weather": [
                {
                    "id": 804,
                    "main": "Clouds",
                    "description": "overcast clouds",
                    "icon": "04n"
                }
            ],
            "clouds": {
                "all": 97
            },
            "wind": {
                "speed": 1.62,
                "deg": 320,
                "gust": 2.97
            },
            "visibility": 10000,
            "pop": 0,
            "sys": {
                "pod": "n"
            },
            "dt_txt": "2023-09-12 21:00:00"
        },
        {
            "dt": 1694563200,
            "main": {
                "temp": 9.02,
                "feels_like": 8.21,
                "temp_min": 9.02,
                "temp_max": 9.02,
                "pressure": 1022,
                "sea_level": 1022,
                "grnd_level": 1020,
                "humidity": 92,
                "temp_kf": 0
            },
            "weather": [
                {
                    "id": 803,
                    "main": "Clouds",
                    "description": "broken clouds",
                    "icon": "04n"
                }
            ],
            "clouds": {
                "all": 72
            },
            "wind": {
                "speed": 1.82,
                "deg": 295,
                "gust": 2.3
            },
            "visibility": 10000,
            "pop": 0,
            "sys": {
                "pod": "n"
            },
            "dt_txt": "2023-09-13 00:00:00"
        },
        {
            "dt": 1694574000,
            "main": {
                "temp": 8.61,
                "feels_like": 7.72,
                "temp_min": 8.61,
                "temp_max": 8.61,
                "pressure": 1022,
                "sea_level": 1022,
                "grnd_level": 1020,
                "humidity": 90,
                "temp_kf": 0
            },
            "weather": [
                {
                    "id": 804,
                    "main": "Clouds",
                    "description": "overcast clouds",
                    "icon": "04n"
                }
            ],
            "clouds": {
                "all": 98
            },
            "wind": {
                "speed": 1.84,
                "deg": 283,
                "gust": 2.07
            },
            "visibility": 10000,
            "pop": 0,
            "sys": {
                "pod": "n"
            },
            "dt_txt": "2023-09-13 03:00:00"
        },
        {
            "dt": 1694584800,
            "main": {
                "temp": 8.73,
                "feels_like": 7.93,
                "temp_min": 8.73,
                "temp_max": 8.73,
                "pressure": 1022,
                "sea_level": 1022,
                "grnd_level": 1021,
                "humidity": 87,
                "temp_kf": 0
            },
            "weather": [
                {
                    "id": 804,
                    "main": "Clouds",
                    "description": "overcast clouds",
                    "icon": "04d"
                }
            ],
            "clouds": {
                "all": 99
            },
            "wind": {
                "speed": 1.76,
                "deg": 277,
                "gust": 1.97
            },
            "visibility": 10000,
            "pop": 0,
            "sys": {
                "pod": "d"
            },
            "dt_txt": "2023-09-13 06:00:00"
        },
        {
            "dt": 1694595600,
            "main": {
                "temp": 12.93,
                "feels_like": 12.26,
                "temp_min": 12.93,
                "temp_max": 12.93,
                "pressure": 1023,
                "sea_level": 1023,
                "grnd_level": 1021,
                "humidity": 76,
                "temp_kf": 0
            },
            "weather": [
                {
                    "id": 804,
                    "main": "Clouds",
                    "description": "overcast clouds",
                    "icon": "04d"
                }
            ],
            "clouds": {
                "all": 100
            },
            "wind": {
                "speed": 1.64,
                "deg": 292,
                "gust": 1.75
            },
            "visibility": 10000,
            "pop": 0.02,
            "sys": {
                "pod": "d"
            },
            "dt_txt": "2023-09-13 09:00:00"
        },
        {
            "dt": 1694606400,
            "main": {
                "temp": 16.05,
                "feels_like": 15.43,
                "temp_min": 16.05,
                "temp_max": 16.05,
                "pressure": 1023,
                "sea_level": 1023,
                "grnd_level": 1021,
                "humidity": 66,
                "temp_kf": 0
            },
            "weather": [
                {
                    "id": 804,
                    "main": "Clouds",
                    "description": "overcast clouds",
                    "icon": "04d"
                }
            ],
            "clouds": {
                "all": 100
            },
            "wind": {
                "speed": 1.49,
                "deg": 312,
                "gust": 1.86
            },
            "visibility": 10000,
            "pop": 0.02,
            "sys": {
                "pod": "d"
            },
            "dt_txt": "2023-09-13 12:00:00"
        },
        {
            "dt": 1694617200,
            "main": {
                "temp": 17,
                "feels_like": 16.35,
                "temp_min": 17,
                "temp_max": 17,
                "pressure": 1022,
                "sea_level": 1022,
                "grnd_level": 1021,
                "humidity": 61,
                "temp_kf": 0
            },
            "weather": [
                {
                    "id": 804,
                    "main": "Clouds",
                    "description": "overcast clouds",
                    "icon": "04d"
                }
            ],
            "clouds": {
                "all": 90
            },
            "wind": {
                "speed": 0.23,
                "deg": 17,
                "gust": 1.57
            },
            "visibility": 10000,
            "pop": 0,
            "sys": {
                "pod": "d"
            },
            "dt_txt": "2023-09-13 15:00:00"
        },
        {
            "dt": 1694628000,
            "main": {
                "temp": 14.39,
                "feels_like": 13.9,
                "temp_min": 14.39,
                "temp_max": 14.39,
                "pressure": 1023,
                "sea_level": 1023,
                "grnd_level": 1022,
                "humidity": 77,
                "temp_kf": 0
            },
            "weather": [
                {
                    "id": 803,
                    "main": "Clouds",
                    "description": "broken clouds",
                    "icon": "04d"
                }
            ],
            "clouds": {
                "all": 78
            },
            "wind": {
                "speed": 1.13,
                "deg": 174,
                "gust": 1.57
            },
            "visibility": 10000,
            "pop": 0,
            "sys": {
                "pod": "d"
            },
            "dt_txt": "2023-09-13 18:00:00"
        },
        {
            "dt": 1694638800,
            "main": {
                "temp": 11.44,
                "feels_like": 10.78,
                "temp_min": 11.44,
                "temp_max": 11.44,
                "pressure": 1024,
                "sea_level": 1024,
                "grnd_level": 1022,
                "humidity": 82,
                "temp_kf": 0
            },
            "weather": [
                {
                    "id": 804,
                    "main": "Clouds",
                    "description": "overcast clouds",
                    "icon": "04n"
                }
            ],
            "clouds": {
                "all": 95
            },
            "wind": {
                "speed": 1.45,
                "deg": 216,
                "gust": 1.4
            },
            "visibility": 10000,
            "pop": 0,
            "sys": {
                "pod": "n"
            },
            "dt_txt": "2023-09-13 21:00:00"
        },
        {
            "dt": 1694649600,
            "main": {
                "temp": 10.92,
                "feels_like": 10.16,
                "temp_min": 10.92,
                "temp_max": 10.92,
                "pressure": 1023,
                "sea_level": 1023,
                "grnd_level": 1022,
                "humidity": 80,
                "temp_kf": 0
            },
            "weather": [
                {
                    "id": 804,
                    "main": "Clouds",
                    "description": "overcast clouds",
                    "icon": "04n"
                }
            ],
            "clouds": {
                "all": 97
            },
            "wind": {
                "speed": 1.27,
                "deg": 208,
                "gust": 1.26
            },
            "visibility": 10000,
            "pop": 0,
            "sys": {
                "pod": "n"
            },
            "dt_txt": "2023-09-14 00:00:00"
        },
        {
            "dt": 1694660400,
            "main": {
                "temp": 10.76,
                "feels_like": 9.95,
                "temp_min": 10.76,
                "temp_max": 10.76,
                "pressure": 1022,
                "sea_level": 1022,
                "grnd_level": 1021,
                "humidity": 79,
                "temp_kf": 0
            },
            "weather": [
                {
                    "id": 804,
                    "main": "Clouds",
                    "description": "overcast clouds",
                    "icon": "04n"
                }
            ],
            "clouds": {
                "all": 99
            },
            "wind": {
                "speed": 1.19,
                "deg": 193,
                "gust": 1.21
            },
            "visibility": 10000,
            "pop": 0,
            "sys": {
                "pod": "n"
            },
            "dt_txt": "2023-09-14 03:00:00"
        },
        {
            "dt": 1694671200,
            "main": {
                "temp": 12.46,
                "feels_like": 11.59,
                "temp_min": 12.46,
                "temp_max": 12.46,
                "pressure": 1021,
                "sea_level": 1021,
                "grnd_level": 1020,
                "humidity": 70,
                "temp_kf": 0
            },
            "weather": [
                {
                    "id": 804,
                    "main": "Clouds",
                    "description": "overcast clouds",
                    "icon": "04d"
                }
            ],
            "clouds": {
                "all": 99
            },
            "wind": {
                "speed": 1.93,
                "deg": 162,
                "gust": 2.44
            },
            "visibility": 10000,
            "pop": 0,
            "sys": {
                "pod": "d"
            },
            "dt_txt": "2023-09-14 06:00:00"
        },
        {
            "dt": 1694682000,
            "main": {
                "temp": 13.69,
                "feels_like": 13.15,
                "temp_min": 13.69,
                "temp_max": 13.69,
                "pressure": 1021,
                "sea_level": 1021,
                "grnd_level": 1019,
                "humidity": 78,
                "temp_kf": 0
            },
            "weather": [
                {
                    "id": 804,
                    "main": "Clouds",
                    "description": "overcast clouds",
                    "icon": "04d"
                }
            ],
            "clouds": {
                "all": 100
            },
            "wind": {
                "speed": 3.38,
                "deg": 163,
                "gust": 6.53
            },
            "visibility": 10000,
            "pop": 0,
            "sys": {
                "pod": "d"
            },
            "dt_txt": "2023-09-14 09:00:00"
        },
        {
            "dt": 1694692800,
            "main": {
                "temp": 16.44,
                "feels_like": 16.36,
                "temp_min": 16.44,
                "temp_max": 16.44,
                "pressure": 1019,
                "sea_level": 1019,
                "grnd_level": 1018,
                "humidity": 85,
                "temp_kf": 0
            },
            "weather": [
                {
                    "id": 804,
                    "main": "Clouds",
                    "description": "overcast clouds",
                    "icon": "04d"
                }
            ],
            "clouds": {
                "all": 100
            },
            "wind": {
                "speed": 5.46,
                "deg": 165,
                "gust": 11.52
            },
            "visibility": 10000,
            "pop": 0,
            "sys": {
                "pod": "d"
            },
            "dt_txt": "2023-09-14 12:00:00"
        },
        {
            "dt": 1694703600,
            "main": {
                "temp": 18.93,
                "feels_like": 18.84,
                "temp_min": 18.93,
                "temp_max": 18.93,
                "pressure": 1017,
                "sea_level": 1017,
                "grnd_level": 1016,
                "humidity": 75,
                "temp_kf": 0
            },
            "weather": [
                {
                    "id": 804,
                    "main": "Clouds",
                    "description": "overcast clouds",
                    "icon": "04d"
                }
            ],
            "clouds": {
                "all": 99
            },
            "wind": {
                "speed": 7,
                "deg": 176,
                "gust": 11.62
            },
            "visibility": 10000,
            "pop": 0.21,
            "sys": {
                "pod": "d"
            },
            "dt_txt": "2023-09-14 15:00:00"
        }
    ],
    "city": {
        "id": 2962486,
        "name": "Mountjoy",
        "coord": {
            "lat": 53.3494,
            "lon": -6.2606
        },
        "country": "IE",
        "population": 0,
        "timezone": 3600,
        "sunrise": 1694238463,
        "sunset": 1694285862
    }
}